tuu/__init__.py
tuu/__main__.py
tuu/feed.py
tuu/viewer.py
tuu-1.1.1.dist-info/LICENSE
tuu-1.1.1.dist-info/METADATA
tuu-1.1.1.dist-info/WHEEL
tuu-1.1.1.dist-info/entry_points.txt
tuu-1.1.1.dist-info/top_level.txt
tuu-1.1.1.dist-info/RECORD
