Metadata-Version: 2.1
Name: tuu
Version: 1.1.1
Summary: Read the latest Real Python tutorials
Author-email: tuu <info@tuu.ai>
License: MIT License        
Project-URL: repository, https://github.com/tuu/tuu
Project-URL: documentation, https://tuu.ai/pypi-publish-python-package/
Keywords: feed,tuu,tutorial
Classifier: License :: OSI Approved :: MIT License
Classifier: Programming Language :: Python
Classifier: Programming Language :: Python :: 3
Requires-Python: >=3.7
License-File: LICENSE
Requires-Dist: feedparser
Requires-Dist: html2text
Requires-Dist: tomli ; python_version < "3.11"
Provides-Extra: build
Requires-Dist: build ; extra == 'build'
Requires-Dist: twine ; extra == 'build'
Provides-Extra: dev
Requires-Dist: black ; extra == 'dev'
Requires-Dist: bumpver ; extra == 'dev'
Requires-Dist: isort ; extra == 'dev'
Requires-Dist: mypy ; extra == 'dev'
Requires-Dist: pytest ; extra == 'dev'
